{
  "ticker": "SPY",
  "timestamp": "2026-03-28T01:39:30.531719",
  "current_price": 594.1,
  "forecast_minutes": 60,
  "technical_indicators": {
    "rsi": 74.48,
    "macd": {
      "line": 2.8937,
      "signal": 2.6043,
      "histogram": 0.2894
    },
    "bollinger_bands": {
      "upper": 571.03,
      "middle": 549.14,
      "lower": 527.26
    }
  },
  "bsm_analysis": {
    "greeks": {
      "delta": 0.537,
      "gamma": 0.007047,
      "theta": -0.4156,
      "vega": 0.6766,
      "rho": 0.2427
    },
    "atm_call_price": 23.73,
    "atm_put_price": 21.17,
    "implied_move": 0.82
  },
  "prediction": {
    "signal": "NEUTRAL",
    "score": -1,
    "confidence": 25.0,
    "reasons": [
      "RSI indicates overbought conditions",
      "MACD histogram positive (bullish momentum)"
    ],
    "target_price": 594.33,
    "support": 591.01,
    "resistance": 597.45
  },
  "simulation": {
    "statistics": {
      "mean": 594.327304859397,
      "std": 4.849747266334452,
      "p05": 586.4110666210353,
      "p25": 591.0130344329193,
      "p50": 594.2539637062418,
      "p75": 597.4501746131739,
      "p95": 602.1514936501095,
      "min": 580.0887242524411,
      "max": 611.8773077374634
    },
    "simulations": 1000,
    "volatility": 0.3309
  }
}