{
  "ticker": "SPY",
  "timestamp": "2026-04-12T15:54:03.021689",
  "current_price": 594.1,
  "forecast_minutes": 60,
  "technical_indicators": {
    "rsi": 60.93,
    "macd": {
      "line": 1.9038,
      "signal": 1.7134,
      "histogram": 0.1904
    },
    "bollinger_bands": {
      "upper": 583.6,
      "middle": 568.49,
      "lower": 553.37
    }
  },
  "bsm_analysis": {
    "greeks": {
      "delta": 0.539,
      "gamma": 0.010015,
      "theta": -0.3059,
      "vega": 0.6762,
      "rho": 0.2492
    },
    "atm_call_price": 17.09,
    "atm_put_price": 14.53,
    "implied_move": 0.57
  },
  "prediction": {
    "signal": "NEUTRAL",
    "score": 1,
    "confidence": 25.0,
    "reasons": [
      "MACD histogram positive (bullish momentum)"
    ],
    "target_price": 594.15,
    "support": 591.89,
    "resistance": 596.55
  },
  "simulation": {
    "statistics": {
      "mean": 594.1517897269106,
      "std": 3.373468386174588,
      "p05": 588.56679828228,
      "p25": 591.8907964602056,
      "p50": 594.2042149038873,
      "p75": 596.549270537256,
      "p95": 599.5388858960209,
      "min": 583.9188076241386,
      "max": 606.3990742414471
    },
    "simulations": 1000,
    "volatility": 0.2328
  }
}