{
  "ticker": "SPY (S&P 500 Proxy)",
  "timestamp": "2026-03-20T14:09:40.693792+00:00",
  "current_price": 652.92,
  "market_state": {
    "is_open": true,
    "minutes_to_close": 350,
    "next_close_time": "2026-03-20 16:00:00 ET",
    "data_source": "yahoo_finance",
    "previous_close": 658.003,
    "day_high": 656.3599853515625,
    "day_low": 652.6699829101562,
    "volume": 17045945
  },
  "closing_projection": {
    "projected_close": 652.91,
    "median_close": 652.92,
    "probability_above_current": 50.08,
    "probability_below_current": 49.92,
    "probability_ranges": {
      "prob_above_current": 50.08,
      "prob_below_current": 49.92,
      "prob_up_0_5pct": 28.0,
      "prob_up_1pct": 12.5,
      "prob_down_0_5pct": 28.56,
      "prob_down_1pct": 12.8,
      "prob_within_0_5pct": 43.44,
      "prob_within_1pct": 74.7
    },
    "confidence_intervals": {
      "50%": [
        649.03,
        656.72
      ],
      "80%": [
        645.59,
        660.26
      ],
      "90%": [
        643.42,
        662.41
      ]
    },
    "price_targets": {
      "projected_close": 652.91,
      "median_close": 652.92,
      "support": 649.03,
      "resistance": 656.72,
      "strong_support": 643.42,
      "strong_resistance": 662.41
    }
  },
  "minute_projection": {
    "current_price": 652.92,
    "projected_next_minute": 652.92,
    "one_minute_std": 0.3134,
    "one_minute_range": [
      652.4,
      653.43
    ],
    "prob_up_next_minute": 49.72,
    "prob_down_next_minute": 50.28
  },
  "hourly_projections": [
    {
      "hour_label": "+1h",
      "projected_price": 652.96,
      "probability_up": 50.06,
      "probability_down": 49.94,
      "confidence_interval_low": 649.88,
      "confidence_interval_high": 656.09,
      "expected_range": 6.21,
      "volatility": 2.4074
    },
    {
      "hour_label": "+2h",
      "projected_price": 653.02,
      "probability_up": 51.88,
      "probability_down": 48.12,
      "confidence_interval_low": 648.8,
      "confidence_interval_high": 657.26,
      "expected_range": 8.46,
      "volatility": 3.3299
    },
    {
      "hour_label": "+3h",
      "projected_price": 652.97,
      "probability_up": 50.08,
      "probability_down": 49.92,
      "confidence_interval_low": 647.57,
      "confidence_interval_high": 658.49,
      "expected_range": 10.91,
      "volatility": 4.2098
    },
    {
      "hour_label": "+4h",
      "projected_price": 653.07,
      "probability_up": 51.12,
      "probability_down": 48.88,
      "confidence_interval_low": 647.01,
      "confidence_interval_high": 659.19,
      "expected_range": 12.19,
      "volatility": 4.7555
    },
    {
      "hour_label": "+5h",
      "projected_price": 653.06,
      "probability_up": 51.0,
      "probability_down": 49.0,
      "confidence_interval_low": 646.24,
      "confidence_interval_high": 659.85,
      "expected_range": 13.61,
      "volatility": 5.2984
    },
    {
      "hour_label": "Close (5.8h)",
      "projected_price": 653.18,
      "probability_up": 51.2,
      "probability_down": 48.8,
      "confidence_interval_low": 645.74,
      "confidence_interval_high": 660.8,
      "expected_range": 15.06,
      "volatility": 5.8601
    }
  ],
  "technical_indicators": {
    "rsi": 56.34,
    "macd": {
      "line": 0.1337,
      "signal": 0.1204,
      "histogram": 0.0134
    },
    "bollinger_bands": {
      "upper": 654.84,
      "middle": 645.2,
      "lower": 635.57
    }
  },
  "bsm_analysis": {
    "greeks": {
      "delta": 0.5486,
      "gamma": 0.014174,
      "theta": -0.2341,
      "vega": 0.7412,
      "rho": 0.2841
    },
    "atm_call_price": 12.58,
    "atm_put_price": 9.77,
    "implied_move_pct": 0.88
  },
  "simulation": {
    "statistics": {
      "mean": 652.9083,
      "std": 5.7255,
      "p05": 643.4215,
      "p10": 645.5888,
      "p25": 649.03,
      "p50": 652.9245,
      "p75": 656.7206,
      "p90": 660.2634,
      "p95": 662.4096,
      "min": 632.2945,
      "max": 674.1932,
      "skewness": 0.0295,
      "kurtosis": -0.0085
    },
    "simulations": 5000,
    "volatility": 0.1492,
    "forecast_minutes": 350
  },
  "signal": "NEUTRAL",
  "confidence": 25.0,
  "data_sources_used": [
    "yahoo_finance",
    "yfinance_data/yfinance.dat",
    "dji_1pm_close/prediction_results.json",
    "market_prediction/latest_prediction.json"
  ]
}