{
  "ticker": "SPY (S&P 500 Proxy)",
  "timestamp": "2026-05-16T18:31:35.719827+00:00",
  "current_price": 739.17,
  "market_state": {
    "is_open": false,
    "minutes_to_close": 2968,
    "next_close_time": "2026-05-18 16:00:00 ET",
    "data_source": "yahoo_finance",
    "previous_close": 748.17,
    "day_high": 743.3400268554688,
    "day_low": 738.0700073242188,
    "volume": 59580378
  },
  "closing_projection": {
    "projected_close": 740.21,
    "median_close": 739.95,
    "probability_above_current": 51.62,
    "probability_below_current": 48.38,
    "probability_ranges": {
      "prob_above_current": 51.62,
      "prob_below_current": 48.38,
      "prob_up_0_5pct": 44.52,
      "prob_up_1pct": 37.56,
      "prob_down_0_5pct": 41.22,
      "prob_down_1pct": 34.0,
      "prob_within_0_5pct": 14.26,
      "prob_within_1pct": 28.44
    },
    "confidence_intervals": {
      "50%": [
        726.36,
        753.96
      ],
      "80%": [
        714.81,
        766.32
      ],
      "90%": [
        706.76,
        773.31
      ]
    },
    "price_targets": {
      "projected_close": 740.21,
      "median_close": 739.95,
      "support": 726.36,
      "resistance": 753.96,
      "strong_support": 706.76,
      "strong_resistance": 773.31
    }
  },
  "minute_projection": {
    "current_price": 739.17,
    "projected_next_minute": 739.17,
    "one_minute_std": 0.3791,
    "one_minute_range": [
      738.54,
      739.78
    ],
    "prob_up_next_minute": 49.7,
    "prob_down_next_minute": 50.3
  },
  "hourly_projections": [
    {
      "hour_label": "+1h",
      "projected_price": 739.33,
      "probability_up": 53.12,
      "probability_down": 46.88,
      "confidence_interval_low": 735.52,
      "confidence_interval_high": 743.05,
      "expected_range": 7.53,
      "volatility": 2.9522
    },
    {
      "hour_label": "+2h",
      "projected_price": 739.24,
      "probability_up": 50.48,
      "probability_down": 49.52,
      "confidence_interval_low": 733.98,
      "confidence_interval_high": 744.46,
      "expected_range": 10.48,
      "volatility": 4.1474
    },
    {
      "hour_label": "+3h",
      "projected_price": 739.33,
      "probability_up": 51.0,
      "probability_down": 49.0,
      "confidence_interval_low": 732.71,
      "confidence_interval_high": 745.92,
      "expected_range": 13.21,
      "volatility": 5.1619
    },
    {
      "hour_label": "+4h",
      "projected_price": 739.29,
      "probability_up": 50.64,
      "probability_down": 49.36,
      "confidence_interval_low": 731.76,
      "confidence_interval_high": 746.74,
      "expected_range": 14.98,
      "volatility": 5.8655
    },
    {
      "hour_label": "+5h",
      "projected_price": 739.38,
      "probability_up": 51.3,
      "probability_down": 48.7,
      "confidence_interval_low": 731.05,
      "confidence_interval_high": 747.71,
      "expected_range": 16.66,
      "volatility": 6.629
    },
    {
      "hour_label": "+6h",
      "projected_price": 739.24,
      "probability_up": 49.8,
      "probability_down": 50.2,
      "confidence_interval_low": 729.83,
      "confidence_interval_high": 748.73,
      "expected_range": 18.9,
      "volatility": 7.3387
    },
    {
      "hour_label": "+7h",
      "projected_price": 739.24,
      "probability_up": 49.84,
      "probability_down": 50.16,
      "confidence_interval_low": 729.11,
      "confidence_interval_high": 749.62,
      "expected_range": 20.51,
      "volatility": 7.9738
    },
    {
      "hour_label": "+8h",
      "projected_price": 739.35,
      "probability_up": 50.66,
      "probability_down": 49.34,
      "confidence_interval_low": 728.74,
      "confidence_interval_high": 750.11,
      "expected_range": 21.37,
      "volatility": 8.3904
    },
    {
      "hour_label": "+9h",
      "projected_price": 739.27,
      "probability_up": 50.24,
      "probability_down": 49.76,
      "confidence_interval_low": 728.04,
      "confidence_interval_high": 750.64,
      "expected_range": 22.6,
      "volatility": 8.7954
    },
    {
      "hour_label": "+10h",
      "projected_price": 739.42,
      "probability_up": 51.36,
      "probability_down": 48.64,
      "confidence_interval_low": 727.21,
      "confidence_interval_high": 751.58,
      "expected_range": 24.37,
      "volatility": 9.4495
    },
    {
      "hour_label": "+11h",
      "projected_price": 739.48,
      "probability_up": 50.64,
      "probability_down": 49.36,
      "confidence_interval_low": 726.93,
      "confidence_interval_high": 752.09,
      "expected_range": 25.16,
      "volatility": 9.8486
    },
    {
      "hour_label": "+12h",
      "projected_price": 739.31,
      "probability_up": 49.92,
      "probability_down": 50.08,
      "confidence_interval_low": 726.44,
      "confidence_interval_high": 752.24,
      "expected_range": 25.8,
      "volatility": 10.1028
    },
    {
      "hour_label": "+13h",
      "projected_price": 739.7,
      "probability_up": 51.84,
      "probability_down": 48.16,
      "confidence_interval_low": 726.08,
      "confidence_interval_high": 753.35,
      "expected_range": 27.28,
      "volatility": 10.817
    },
    {
      "hour_label": "+14h",
      "projected_price": 739.34,
      "probability_up": 49.84,
      "probability_down": 50.16,
      "confidence_interval_low": 725.15,
      "confidence_interval_high": 753.89,
      "expected_range": 28.74,
      "volatility": 11.1503
    },
    {
      "hour_label": "+15h",
      "projected_price": 739.43,
      "probability_up": 49.68,
      "probability_down": 50.32,
      "confidence_interval_low": 724.88,
      "confidence_interval_high": 754.44,
      "expected_range": 29.56,
      "volatility": 11.5291
    },
    {
      "hour_label": "+16h",
      "projected_price": 739.31,
      "probability_up": 50.58,
      "probability_down": 49.42,
      "confidence_interval_low": 724.25,
      "confidence_interval_high": 754.45,
      "expected_range": 30.2,
      "volatility": 11.9561
    },
    {
      "hour_label": "+17h",
      "projected_price": 739.49,
      "probability_up": 50.76,
      "probability_down": 49.24,
      "confidence_interval_low": 723.87,
      "confidence_interval_high": 755.57,
      "expected_range": 31.7,
      "volatility": 12.3291
    },
    {
      "hour_label": "+18h",
      "projected_price": 739.91,
      "probability_up": 52.9,
      "probability_down": 47.1,
      "confidence_interval_low": 723.59,
      "confidence_interval_high": 756.13,
      "expected_range": 32.54,
      "volatility": 12.5256
    },
    {
      "hour_label": "+19h",
      "projected_price": 739.96,
      "probability_up": 51.98,
      "probability_down": 48.02,
      "confidence_interval_low": 723.43,
      "confidence_interval_high": 757.01,
      "expected_range": 33.59,
      "volatility": 12.989
    },
    {
      "hour_label": "+20h",
      "projected_price": 739.66,
      "probability_up": 51.42,
      "probability_down": 48.58,
      "confidence_interval_low": 722.47,
      "confidence_interval_high": 756.68,
      "expected_range": 34.21,
      "volatility": 13.3613
    },
    {
      "hour_label": "+21h",
      "projected_price": 740.01,
      "probability_up": 51.72,
      "probability_down": 48.28,
      "confidence_interval_low": 722.93,
      "confidence_interval_high": 758.0,
      "expected_range": 35.07,
      "volatility": 13.7799
    },
    {
      "hour_label": "+22h",
      "projected_price": 739.87,
      "probability_up": 51.88,
      "probability_down": 48.12,
      "confidence_interval_low": 722.28,
      "confidence_interval_high": 757.96,
      "expected_range": 35.68,
      "volatility": 13.8794
    },
    {
      "hour_label": "+23h",
      "projected_price": 739.74,
      "probability_up": 51.64,
      "probability_down": 48.36,
      "confidence_interval_low": 721.47,
      "confidence_interval_high": 757.64,
      "expected_range": 36.17,
      "volatility": 14.1242
    },
    {
      "hour_label": "+24h",
      "projected_price": 739.88,
      "probability_up": 51.66,
      "probability_down": 48.34,
      "confidence_interval_low": 721.32,
      "confidence_interval_high": 758.37,
      "expected_range": 37.05,
      "volatility": 14.518
    },
    {
      "hour_label": "+25h",
      "projected_price": 739.94,
      "probability_up": 51.42,
      "probability_down": 48.58,
      "confidence_interval_low": 720.67,
      "confidence_interval_high": 759.55,
      "expected_range": 38.88,
      "volatility": 15.2684
    },
    {
      "hour_label": "+26h",
      "projected_price": 739.77,
      "probability_up": 50.78,
      "probability_down": 49.22,
      "confidence_interval_low": 720.54,
      "confidence_interval_high": 759.36,
      "expected_range": 38.82,
      "volatility": 15.1054
    },
    {
      "hour_label": "+27h",
      "projected_price": 739.22,
      "probability_up": 49.58,
      "probability_down": 50.42,
      "confidence_interval_low": 719.79,
      "confidence_interval_high": 759.34,
      "expected_range": 39.54,
      "volatility": 15.281
    },
    {
      "hour_label": "+28h",
      "projected_price": 739.94,
      "probability_up": 51.02,
      "probability_down": 48.98,
      "confidence_interval_low": 719.82,
      "confidence_interval_high": 760.81,
      "expected_range": 40.99,
      "volatility": 15.7702
    },
    {
      "hour_label": "+29h",
      "projected_price": 739.96,
      "probability_up": 52.18,
      "probability_down": 47.82,
      "confidence_interval_low": 719.33,
      "confidence_interval_high": 760.34,
      "expected_range": 41.01,
      "volatility": 15.9071
    },
    {
      "hour_label": "+30h",
      "projected_price": 740.16,
      "probability_up": 52.36,
      "probability_down": 47.64,
      "confidence_interval_low": 719.21,
      "confidence_interval_high": 760.7,
      "expected_range": 41.49,
      "volatility": 16.2516
    },
    {
      "hour_label": "+31h",
      "projected_price": 739.74,
      "probability_up": 50.46,
      "probability_down": 49.54,
      "confidence_interval_low": 719.2,
      "confidence_interval_high": 760.66,
      "expected_range": 41.46,
      "volatility": 16.3706
    },
    {
      "hour_label": "+32h",
      "projected_price": 739.79,
      "probability_up": 51.16,
      "probability_down": 48.84,
      "confidence_interval_low": 718.32,
      "confidence_interval_high": 761.4,
      "expected_range": 43.08,
      "volatility": 16.7706
    },
    {
      "hour_label": "+33h",
      "projected_price": 740.16,
      "probability_up": 51.08,
      "probability_down": 48.92,
      "confidence_interval_low": 718.36,
      "confidence_interval_high": 762.43,
      "expected_range": 44.07,
      "volatility": 17.2206
    },
    {
      "hour_label": "+34h",
      "projected_price": 739.98,
      "probability_up": 51.7,
      "probability_down": 48.3,
      "confidence_interval_low": 717.89,
      "confidence_interval_high": 762.0,
      "expected_range": 44.11,
      "volatility": 17.2943
    },
    {
      "hour_label": "+35h",
      "projected_price": 739.79,
      "probability_up": 50.9,
      "probability_down": 49.1,
      "confidence_interval_low": 717.72,
      "confidence_interval_high": 761.46,
      "expected_range": 43.74,
      "volatility": 17.0205
    },
    {
      "hour_label": "+36h",
      "projected_price": 739.67,
      "probability_up": 50.44,
      "probability_down": 49.56,
      "confidence_interval_low": 716.58,
      "confidence_interval_high": 762.41,
      "expected_range": 45.83,
      "volatility": 17.8946
    },
    {
      "hour_label": "+37h",
      "projected_price": 740.35,
      "probability_up": 52.18,
      "probability_down": 47.82,
      "confidence_interval_low": 717.0,
      "confidence_interval_high": 764.04,
      "expected_range": 47.04,
      "volatility": 18.2618
    },
    {
      "hour_label": "+38h",
      "projected_price": 739.42,
      "probability_up": 49.84,
      "probability_down": 50.16,
      "confidence_interval_low": 715.71,
      "confidence_interval_high": 763.28,
      "expected_range": 47.57,
      "volatility": 18.5312
    },
    {
      "hour_label": "+39h",
      "projected_price": 740.12,
      "probability_up": 51.68,
      "probability_down": 48.32,
      "confidence_interval_low": 716.53,
      "confidence_interval_high": 763.74,
      "expected_range": 47.22,
      "volatility": 18.3427
    },
    {
      "hour_label": "+40h",
      "projected_price": 740.06,
      "probability_up": 51.08,
      "probability_down": 48.92,
      "confidence_interval_low": 716.26,
      "confidence_interval_high": 763.83,
      "expected_range": 47.58,
      "volatility": 18.5481
    },
    {
      "hour_label": "+41h",
      "projected_price": 740.22,
      "probability_up": 51.48,
      "probability_down": 48.52,
      "confidence_interval_low": 716.25,
      "confidence_interval_high": 765.07,
      "expected_range": 48.82,
      "volatility": 18.8723
    },
    {
      "hour_label": "+42h",
      "projected_price": 740.25,
      "probability_up": 51.62,
      "probability_down": 48.38,
      "confidence_interval_low": 715.45,
      "confidence_interval_high": 765.25,
      "expected_range": 49.8,
      "volatility": 19.2434
    },
    {
      "hour_label": "+43h",
      "projected_price": 740.36,
      "probability_up": 52.52,
      "probability_down": 47.48,
      "confidence_interval_low": 715.41,
      "confidence_interval_high": 765.12,
      "expected_range": 49.71,
      "volatility": 19.3445
    },
    {
      "hour_label": "+44h",
      "projected_price": 740.28,
      "probability_up": 51.86,
      "probability_down": 48.14,
      "confidence_interval_low": 715.62,
      "confidence_interval_high": 765.51,
      "expected_range": 49.89,
      "volatility": 19.6875
    },
    {
      "hour_label": "+45h",
      "projected_price": 740.18,
      "probability_up": 51.64,
      "probability_down": 48.36,
      "confidence_interval_low": 714.72,
      "confidence_interval_high": 765.6,
      "expected_range": 50.88,
      "volatility": 20.0419
    },
    {
      "hour_label": "+46h",
      "projected_price": 740.17,
      "probability_up": 50.86,
      "probability_down": 49.14,
      "confidence_interval_low": 715.15,
      "confidence_interval_high": 766.05,
      "expected_range": 50.9,
      "volatility": 20.0643
    },
    {
      "hour_label": "+47h",
      "projected_price": 739.73,
      "probability_up": 50.48,
      "probability_down": 49.52,
      "confidence_interval_low": 713.33,
      "confidence_interval_high": 766.71,
      "expected_range": 53.38,
      "volatility": 20.6832
    },
    {
      "hour_label": "+48h",
      "projected_price": 740.17,
      "probability_up": 51.64,
      "probability_down": 48.36,
      "confidence_interval_low": 714.62,
      "confidence_interval_high": 765.93,
      "expected_range": 51.31,
      "volatility": 20.2915
    },
    {
      "hour_label": "+49h",
      "projected_price": 740.23,
      "probability_up": 51.38,
      "probability_down": 48.62,
      "confidence_interval_low": 713.59,
      "confidence_interval_high": 766.94,
      "expected_range": 53.34,
      "volatility": 21.0982
    },
    {
      "hour_label": "Close (49.5h)",
      "projected_price": 740.38,
      "probability_up": 51.12,
      "probability_down": 48.88,
      "confidence_interval_low": 713.97,
      "confidence_interval_high": 767.48,
      "expected_range": 53.52,
      "volatility": 20.9602
    }
  ],
  "technical_indicators": {
    "rsi": 60.01,
    "macd": {
      "line": 4.7264,
      "signal": 4.2538,
      "histogram": 0.4726
    },
    "bollinger_bands": {
      "upper": 755.41,
      "middle": 736.12,
      "lower": 716.82
    }
  },
  "bsm_analysis": {
    "greeks": {
      "delta": 0.5462,
      "gamma": 0.011517,
      "theta": -0.2831,
      "vega": 0.8397,
      "rho": 0.3192
    },
    "atm_call_price": 15.35,
    "atm_put_price": 12.16,
    "implied_move_pct": 2.76
  },
  "simulation": {
    "statistics": {
      "mean": 740.2081,
      "std": 20.3998,
      "p05": 706.7601,
      "p10": 714.8055,
      "p25": 726.3608,
      "p50": 739.9515,
      "p75": 753.9616,
      "p90": 766.3234,
      "p95": 773.3113,
      "min": 670.8287,
      "max": 814.4146,
      "skewness": 0.0686,
      "kurtosis": 0.1081
    },
    "simulations": 5000,
    "volatility": 0.1624,
    "forecast_minutes": 2968
  },
  "signal": "BULLISH",
  "confidence": 50.0,
  "data_sources_used": [
    "dji_1pm_close/prediction_results.json",
    "yahoo_finance",
    "yfinance_data/yfinance.dat",
    "market_prediction/latest_prediction.json"
  ]
}