{
  "ticker": "SPY (S&P 500 Proxy)",
  "timestamp": "2026-03-02T21:51:12.890227+00:00",
  "current_price": 686.38,
  "market_state": {
    "is_open": false,
    "minutes_to_close": 1388,
    "next_close_time": "2026-03-03 16:00:00 ET",
    "data_source": "yahoo_finance",
    "previous_close": 685.99,
    "day_high": 688.5499877929688,
    "day_low": 679.1900024414062,
    "volume": 83702843
  },
  "closing_projection": {
    "projected_close": 686.58,
    "median_close": 686.39,
    "probability_above_current": 50.02,
    "probability_below_current": 49.98,
    "probability_ranges": {
      "prob_above_current": 50.02,
      "prob_below_current": 49.98,
      "prob_up_0_5pct": 42.26,
      "prob_up_1pct": 33.64,
      "prob_down_0_5pct": 41.74,
      "prob_down_1pct": 33.9,
      "prob_within_0_5pct": 16.0,
      "prob_within_1pct": 32.46
    },
    "confidence_intervals": {
      "50%": [
        675.09,
        697.54
      ],
      "80%": [
        665.46,
        708.25
      ],
      "90%": [
        659.65,
        714.89
      ]
    },
    "price_targets": {
      "projected_close": 686.58,
      "median_close": 686.39,
      "support": 675.09,
      "resistance": 697.54,
      "strong_support": 659.65,
      "strong_resistance": 714.89
    }
  },
  "minute_projection": {
    "current_price": 686.38,
    "projected_next_minute": 686.39,
    "one_minute_std": 0.4476,
    "one_minute_range": [
      685.65,
      687.13
    ],
    "prob_up_next_minute": 50.1,
    "prob_down_next_minute": 49.9
  },
  "hourly_projections": [
    {
      "hour_label": "+1h",
      "projected_price": 686.35,
      "probability_up": 50.14,
      "probability_down": 49.86,
      "confidence_interval_low": 681.84,
      "confidence_interval_high": 690.77,
      "expected_range": 8.92,
      "volatility": 3.4415
    },
    {
      "hour_label": "+2h",
      "projected_price": 686.32,
      "probability_up": 50.34,
      "probability_down": 49.66,
      "confidence_interval_low": 680.07,
      "confidence_interval_high": 692.63,
      "expected_range": 12.56,
      "volatility": 4.8836
    },
    {
      "hour_label": "+3h",
      "projected_price": 686.4,
      "probability_up": 50.84,
      "probability_down": 49.16,
      "confidence_interval_low": 678.75,
      "confidence_interval_high": 693.99,
      "expected_range": 15.24,
      "volatility": 5.9939
    },
    {
      "hour_label": "+4h",
      "projected_price": 686.42,
      "probability_up": 50.06,
      "probability_down": 49.94,
      "confidence_interval_low": 677.55,
      "confidence_interval_high": 695.19,
      "expected_range": 17.64,
      "volatility": 6.8793
    },
    {
      "hour_label": "+5h",
      "projected_price": 686.44,
      "probability_up": 50.1,
      "probability_down": 49.9,
      "confidence_interval_low": 676.68,
      "confidence_interval_high": 696.4,
      "expected_range": 19.73,
      "volatility": 7.7638
    },
    {
      "hour_label": "+6h",
      "projected_price": 686.21,
      "probability_up": 48.58,
      "probability_down": 51.42,
      "confidence_interval_low": 675.45,
      "confidence_interval_high": 696.95,
      "expected_range": 21.5,
      "volatility": 8.3874
    },
    {
      "hour_label": "+7h",
      "projected_price": 686.58,
      "probability_up": 50.98,
      "probability_down": 49.02,
      "confidence_interval_low": 674.61,
      "confidence_interval_high": 698.56,
      "expected_range": 23.95,
      "volatility": 9.3609
    },
    {
      "hour_label": "+8h",
      "projected_price": 686.28,
      "probability_up": 49.22,
      "probability_down": 50.78,
      "confidence_interval_low": 673.73,
      "confidence_interval_high": 698.73,
      "expected_range": 25.0,
      "volatility": 9.7556
    },
    {
      "hour_label": "+9h",
      "projected_price": 686.74,
      "probability_up": 51.02,
      "probability_down": 48.98,
      "confidence_interval_low": 673.68,
      "confidence_interval_high": 700.43,
      "expected_range": 26.75,
      "volatility": 10.4247
    },
    {
      "hour_label": "+10h",
      "projected_price": 686.56,
      "probability_up": 49.58,
      "probability_down": 50.42,
      "confidence_interval_low": 672.99,
      "confidence_interval_high": 700.65,
      "expected_range": 27.66,
      "volatility": 10.8172
    },
    {
      "hour_label": "+11h",
      "projected_price": 686.58,
      "probability_up": 49.8,
      "probability_down": 50.2,
      "confidence_interval_low": 671.89,
      "confidence_interval_high": 701.65,
      "expected_range": 29.76,
      "volatility": 11.6025
    },
    {
      "hour_label": "+12h",
      "projected_price": 686.54,
      "probability_up": 49.88,
      "probability_down": 50.12,
      "confidence_interval_low": 671.49,
      "confidence_interval_high": 701.96,
      "expected_range": 30.47,
      "volatility": 12.0856
    },
    {
      "hour_label": "+13h",
      "projected_price": 686.59,
      "probability_up": 50.7,
      "probability_down": 49.3,
      "confidence_interval_low": 670.55,
      "confidence_interval_high": 702.69,
      "expected_range": 32.14,
      "volatility": 12.5486
    },
    {
      "hour_label": "+14h",
      "projected_price": 686.88,
      "probability_up": 50.58,
      "probability_down": 49.42,
      "confidence_interval_low": 670.33,
      "confidence_interval_high": 703.75,
      "expected_range": 33.41,
      "volatility": 12.9633
    },
    {
      "hour_label": "+15h",
      "projected_price": 686.64,
      "probability_up": 49.98,
      "probability_down": 50.02,
      "confidence_interval_low": 669.94,
      "confidence_interval_high": 703.62,
      "expected_range": 33.67,
      "volatility": 13.3637
    },
    {
      "hour_label": "+16h",
      "projected_price": 686.9,
      "probability_up": 51.46,
      "probability_down": 48.54,
      "confidence_interval_low": 669.05,
      "confidence_interval_high": 704.86,
      "expected_range": 35.81,
      "volatility": 13.9251
    },
    {
      "hour_label": "+17h",
      "projected_price": 686.9,
      "probability_up": 51.72,
      "probability_down": 48.28,
      "confidence_interval_low": 668.6,
      "confidence_interval_high": 705.91,
      "expected_range": 37.32,
      "volatility": 14.5351
    },
    {
      "hour_label": "+18h",
      "projected_price": 686.52,
      "probability_up": 49.9,
      "probability_down": 50.1,
      "confidence_interval_low": 668.09,
      "confidence_interval_high": 705.32,
      "expected_range": 37.23,
      "volatility": 14.4837
    },
    {
      "hour_label": "+19h",
      "projected_price": 686.61,
      "probability_up": 49.7,
      "probability_down": 50.3,
      "confidence_interval_low": 667.09,
      "confidence_interval_high": 706.35,
      "expected_range": 39.27,
      "volatility": 15.2826
    },
    {
      "hour_label": "+20h",
      "projected_price": 686.45,
      "probability_up": 50.1,
      "probability_down": 49.9,
      "confidence_interval_low": 666.78,
      "confidence_interval_high": 706.47,
      "expected_range": 39.69,
      "volatility": 15.422
    },
    {
      "hour_label": "+21h",
      "projected_price": 686.95,
      "probability_up": 50.5,
      "probability_down": 49.5,
      "confidence_interval_low": 666.19,
      "confidence_interval_high": 707.9,
      "expected_range": 41.7,
      "volatility": 16.0228
    },
    {
      "hour_label": "+22h",
      "projected_price": 686.82,
      "probability_up": 50.18,
      "probability_down": 49.82,
      "confidence_interval_low": 665.46,
      "confidence_interval_high": 708.41,
      "expected_range": 42.94,
      "volatility": 16.4159
    },
    {
      "hour_label": "+23h",
      "projected_price": 686.95,
      "probability_up": 51.7,
      "probability_down": 48.3,
      "confidence_interval_low": 665.41,
      "confidence_interval_high": 708.21,
      "expected_range": 42.8,
      "volatility": 16.6271
    },
    {
      "hour_label": "Close (23.1h)",
      "projected_price": 687.01,
      "probability_up": 50.84,
      "probability_down": 49.16,
      "confidence_interval_low": 665.03,
      "confidence_interval_high": 708.77,
      "expected_range": 43.74,
      "volatility": 17.0241
    }
  ],
  "technical_indicators": {
    "rsi": 55.77,
    "macd": {
      "line": 7.4013,
      "signal": 6.6611,
      "histogram": 0.7401
    },
    "bollinger_bands": {
      "upper": 713.0,
      "middle": 686.92,
      "lower": 660.84
    }
  },
  "bsm_analysis": {
    "greeks": {
      "delta": 0.5409,
      "gamma": 0.009834,
      "theta": -0.3178,
      "vega": 0.7809,
      "rho": 0.2907
    },
    "atm_call_price": 17.58,
    "atm_put_price": 14.63,
    "implied_move_pct": 2.46
  },
  "simulation": {
    "statistics": {
      "mean": 686.5831,
      "std": 16.8667,
      "p05": 659.6515,
      "p10": 665.4599,
      "p25": 675.0936,
      "p50": 686.3891,
      "p75": 697.5426,
      "p90": 708.2522,
      "p95": 714.8933,
      "min": 625.2305,
      "max": 751.9293,
      "skewness": 0.0688,
      "kurtosis": 0.0968
    },
    "simulations": 5000,
    "volatility": 0.2051,
    "forecast_minutes": 1388
  },
  "signal": "NEUTRAL",
  "confidence": 25.0,
  "data_sources_used": [
    "dji_1pm_close/prediction_results.json",
    "yfinance_data/yfinance.dat",
    "market_prediction/latest_prediction.json",
    "yahoo_finance"
  ]
}