{
  "updated": "2026-04-23T14:57:47.945233+00:00",
  "tickers": {
    "JPM": {
      "price": 314.51,
      "volume": 10374611,
      "high52": 337.25,
      "low52": 237.58
    },
    "GS": {
      "price": 944.255,
      "volume": 2398003,
      "high52": 984.7,
      "low52": 523.42
    },
    "BAC": {
      "price": 53.415,
      "volume": 40894606,
      "high52": 57.55,
      "low52": 38.6
    },
    "WFC": {
      "price": 81.26,
      "volume": 17226648,
      "high52": 97.76,
      "low52": 67.5
    },
    "MS": {
      "price": 191.63,
      "volume": 7357690,
      "high52": 194.59,
      "low52": 111.24
    }
  }
}