{
  "updated": "2026-04-27T23:10:38.226412+00:00",
  "tickers": {
    "SPY": {
      "close": 715.16,
      "volume": 685128,
      "high": 715.215,
      "low": 714.96,
      "ts": "2026-04-27 15:59:00-04:00"
    },
    "QQQ": {
      "close": 664.27,
      "volume": 254631,
      "high": 664.27,
      "low": 664.034,
      "ts": "2026-04-27 15:59:00-04:00"
    },
    "DIA": {
      "close": 491.81,
      "volume": 49389,
      "high": 491.86,
      "low": 491.68,
      "ts": "2026-04-27 15:59:00-04:00"
    },
    "IWM": {
      "close": 277.1,
      "volume": 354344,
      "high": 277.13,
      "low": 276.97,
      "ts": "2026-04-27 15:59:00-04:00"
    },
    "AAPL": {
      "close": 267.68,
      "volume": 645524,
      "high": 267.69,
      "low": 267.44,
      "ts": "2026-04-27 15:59:00-04:00"
    },
    "MSFT": {
      "close": 425.06,
      "volume": 461238,
      "high": 425.09,
      "low": 424.66,
      "ts": "2026-04-27 15:59:00-04:00"
    },
    "NVDA": {
      "close": 216.63,
      "volume": 1947460,
      "high": 216.69,
      "low": 216.45,
      "ts": "2026-04-27 15:59:00-04:00"
    },
    "TSLA": {
      "close": 378.7,
      "volume": 665541,
      "high": 378.95,
      "low": 378.5,
      "ts": "2026-04-27 15:59:00-04:00"
    },
    "BTC-USD": {
      "close": 77026.6484,
      "volume": 0,
      "high": 77026.6484,
      "low": 77026.6484,
      "ts": "2026-04-27 23:10:00+00:00"
    },
    "ETH-USD": {
      "close": 2291.1899,
      "volume": 0,
      "high": 2291.1899,
      "low": 2291.1899,
      "ts": "2026-04-27 23:10:00+00:00"
    }
  }
}